reperiods/__init__.py
reperiods/_version.py
reperiods/datasets.py
reperiods/export.py
reperiods/find_RP.py
reperiods/plot.py
reperiods/representative_periods.py
reperiods/temporal_data.py
reperiods/utils.py
reperiods_beta-1.0.3.dist-info/LICENSE
reperiods_beta-1.0.3.dist-info/METADATA
reperiods_beta-1.0.3.dist-info/WHEEL
reperiods_beta-1.0.3.dist-info/top_level.txt
reperiods_beta-1.0.3.dist-info/RECORD
