Metadata-Version: 2.1
Name: reperiods-beta
Version: 1.0.3
Summary: A set of tools to find Representative Periods.
Home-page: UNKNOWN
License: MIT
Platform: UNKNOWN
Classifier: Intended Audience :: Science/Research
Classifier: Topic :: Scientific/Engineering
Requires-Python: >=3.10
License-File: LICENSE
Requires-Dist: pandas >=2.0.3
Requires-Dist: PuLP >=2.7.0
Requires-Dist: plotly >=5.15.0
Requires-Dist: scikit-learn-extra >=0.3.0
Requires-Dist: numpy >=1.25.2
Requires-Dist: nbformat >=4.2.0
Provides-Extra: docs
Requires-Dist: pillow ; extra == 'docs'
Requires-Dist: sphinx ; extra == 'docs'
Requires-Dist: sphinx-gallery ; extra == 'docs'
Requires-Dist: sphinx-rtd-theme ; extra == 'docs'
Requires-Dist: numpydoc ; extra == 'docs'
Requires-Dist: matplotlib ; extra == 'docs'
Provides-Extra: tests
Requires-Dist: pytest ; extra == 'tests'
Requires-Dist: pytest-cov ; extra == 'tests'
Requires-Dist: twine ; extra == 'tests'
Requires-Dist: wheel ; extra == 'tests'
